{
  "description": "Show Flexmonster report",
  "image": "https://raw.githubusercontent.com/zippydoc/Pictograms/master/AddColumn.gif",
  "scriptSettings": {
    "autoLoadTable": [
      "table1",
      "table2"
    ],
    "countries": [
      "US",
      "UK"
    ],
    "languages": [
      "EN"
    ],
    "displayName": "Flexmonster",
    "payingUsersOnly": true,
    "type": "ExpertTableTask",
	"attributes": [
      "1-input","Guest-User","Starter-Screen"
	]
  },
  "menu": [
    {
      "source": "https://api.github.com/repos/zippydoc/menue-snippets/contents/common-snippets/SelectTable.json?ref=main"
    },
    {
      "source": "https://api.github.com/repos/zippydoc/menue-snippets/contents/FlexmonsterOptions.json?ref=main",
      "children": [
        {
          "source": "https://api.github.com/repos/zippydoc/menue-snippets/contents/common-snippets/FormattingWithKeepCurrentInRepeat.json?ref=main",
          "property": "options_box/fields/options.measure_cols/fields",
          "after": "aggregation"
        }
      ]
    },
    {
      "source": "https://api.github.com/repos/zippydoc/menue-snippets/contents/common-snippets/Debug.json?ref=main"
    }
  ],
  "script": "https://api.github.com/repos/zippydoc/basic/contents/Flexmonster.py?ref=master",
  "version": 1.0
}
