{
  "description": "从你的表格中生成一个D3树形图",
  "image": "https://raw.githubusercontent.com/zippydoc/Pictograms/master/D3-Sunburst.gif",
  "scriptSettings": {
    "autoLoadTable": [
    ],
    "countries": [
      "US",
      "UK"
    ],
    "languages": [
      "EN"
    ],
    "displayName": "D3太阳花",
    "payingUsersOnly": false,
    "explanationPicture": "",
    "type": "Create Reports",
	"attributes": [
      "1-input","Guest-User","Starter-Screen"
	]
  },
  "menu": [
    {
      "source": "https://api.github.com/repos/zippydoc/menue-snippets/contents/CN/FlexmonsterInput.json?ref=main"
    },
    {
      "source": "https://api.github.com/repos/zippydoc/menue-snippets/contents/CN/D3SunburstOptions.json?ref=main"
    }
  ],
  "script": "https://api.github.com/repos/zippydoc/basic/contents/D3.py?ref=master",
  "version": 1.0
}