{
  "description": "使综合规划包（损益表、现金流和资产负债表）变得简单",
  "image": "https://raw.githubusercontent.com/zippydoc/Pictograms/master/Delete.gif",
  "scriptSettings": {
    "autoLoadTable": [
    ],
    "countries": [
      "US",
      "UK"
    ],
    "languages": [
      "EN"
    ],
    "displayName": "删除",
    "payingUsersOnly": false,
    "explanationPicture": "https://raw.githubusercontent.com/zippydoc/Pictograms/master/Explanations/Delete.png",
    "type": "Prepare",
    "attributes": [
        "1-input","Guest-User","Starter-Screen"
    ]
  },
  "menu": [
    {
      "source": "https://api.github.com/repos/zippydoc/menue-snippets/contents/common-snippets/CN/SelectTable.json?ref=main",
      "children": [
        {
          "source": "https://api.github.com/repos/zippydoc/menue-snippets/contents/CN/DeleteOptions.json?ref=main",
          "property": "fields"
        }
      ]
    }
  ],
  "script": "https://api.github.com/repos/zippydoc/basic/contents/Delete.py?ref=master",
  "version": 1.0
}