{
  "description": "重命名表格行或列",
  "image": "https://raw.githubusercontent.com/zippydoc/Pictograms/master/Rename.gif",
  "scriptSettings": {
    "autoLoadTable": [
    ],
    "countries": [
      "US",
      "UK"
    ],
    "languages": [
      "CN"
    ],
    "displayName": "重命名",
    "payingUsersOnly": false,
    "type": "ExpertTableTask",
    "attributes": [
        "1-Input","Starter-Screen"
    ]
  },
  "menu": [
    {
      "source": "https://api.github.com/repos/zippydoc/menue-snippets/contents/common-snippets/CN/SelectTable.json?ref=main",
      "children": [
        {
          "source": "https://api.github.com/repos/zippydoc/menue-snippets/contents/CN/RenameTableInput.json?ref=main",
          "property": "fields"
        }
      ]
    },
    {
      "source": "https://api.github.com/repos/zippydoc/menue-snippets/contents/CN/RenameTableOptions.json?ref=main"
    }
  ],
  "script": "https://api.github.com/repos/zippydoc/basic/contents/Rename.py?ref=master",
  "version": 1.0
}